COPYING.txt
MANIFEST.in
README.txt
setup.py
gridproxy/__init__.py
gridproxy/voms.py
gridproxy.egg-info/PKG-INFO
gridproxy.egg-info/SOURCES.txt
gridproxy.egg-info/dependency_links.txt
gridproxy.egg-info/top_level.txt
gridproxy.egg-info/zip-safe