Metadata-Version: 1.1
Name: gridproxy
Version: 0.1
Summary: Small library for working with grid proxy certificates and VOMS extensions
Home-page: https://github.com/abbot/gridproxy
Author: Lev Shamardin
Author-email: shamardin@gmail.com
License: GPLv3+
Keywords: voms,proxy,certificate,x509,grid
Platform: UNKNOWN
Classifier: Development Status :: 4 - Beta
Classifier: License :: OSI Approved :: GNU General Public License v3 or later (GPLv3+)
Classifier: Operating System :: POSIX
Classifier: Programming Language :: Python
Classifier: Topic :: Internet
Classifier: Topic :: Security :: Cryptography
Classifier: Topic :: Software Development :: Libraries :: Python Modules
